vfp2py/VisualFoxpro9Lexer.py
vfp2py/VisualFoxpro9Parser.py
vfp2py/VisualFoxpro9Visitor.py
vfp2py/__init__.py
vfp2py/__main__.py
vfp2py/function_abbreviations.py
vfp2py/fxp_read.py
vfp2py/pythondde.py
vfp2py/reverter.py
vfp2py/vfp2py.py
vfp2py/vfp2py_convert_visitor.py
vfp2py/vfpdatabase.py
vfp2py/vfpfunc.py
vfp2py-0.1.1.dist-info/LICENSE
vfp2py-0.1.1.dist-info/METADATA
vfp2py-0.1.1.dist-info/WHEEL
vfp2py-0.1.1.dist-info/entry_points.txt
vfp2py-0.1.1.dist-info/top_level.txt
vfp2py-0.1.1.dist-info/RECORD
